LICENSE
MANIFEST.in
README.rst
setup.py
leselys/__init__.py
leselys/api.py
leselys/core.py
leselys/feed_finder.py
leselys/helpers.py
leselys/logger.py
leselys/reader.py
leselys/themes.py
leselys/views.py
leselys/worker.py
leselys/wsgi.py
leselys.egg-info/PKG-INFO
leselys.egg-info/SOURCES.txt
leselys.egg-info/dependency_links.txt
leselys.egg-info/not-zip-safe
leselys.egg-info/requires.txt
leselys.egg-info/top_level.txt
leselys/backends/__init__.py
leselys/backends/session/__init__.py
leselys/backends/session/_redis.py
leselys/backends/storage/__init__.py
leselys/backends/storage/_mongodb.py
leselys/backends/storage/_sofart.py
leselys/backends/storage/_storage.py
leselys/externals/__init__.py
leselys/externals/opml.py
leselys/static/css/bootstrap-responsive.css
leselys/static/css/bootstrap-responsive.min.css
leselys/static/css/bootstrap.css
leselys/static/css/bootstrap.min.css
leselys/static/css/flat-ui.css
leselys/static/css/flat-ui.min.css
leselys/static/css/font-awesome.css
leselys/static/css/font-awesome.min.css
leselys/static/css/journal.css
leselys/static/css/journal.min.css
leselys/static/css/leselys.css
leselys/static/css/leselys.min.css
leselys/static/css/readable.css
leselys/static/css/readable.min.css
leselys/static/font/FontAwesome.otf
leselys/static/font/fontawesome-webfont.eot
leselys/static/font/fontawesome-webfont.svg
leselys/static/font/fontawesome-webfont.ttf
leselys/static/font/fontawesome-webfont.woff
leselys/static/img/apple-touch-icon-114x114-precomposed.png
leselys/static/img/apple-touch-icon-72x72-precomposed.png
leselys/static/img/apple-touch-icon-precomposed.png
leselys/static/img/favicon.ico
leselys/static/img/glyphicons-halflings-white.png
leselys/static/img/glyphicons-halflings.png
leselys/static/js/ajax.js
leselys/static/js/api.js
leselys/static/js/crel.js
leselys/static/js/leselys.js
leselys/static/js/leselys.min.js
leselys/static/js/mousetrap.js
leselys/static/js/tinybox.js
leselys/templates/home.html
leselys/templates/layout.debug.html
leselys/templates/layout.html
leselys/templates/login.html
leselys/templates/settings.html
leselys/templates/sidebar.html
leselys/templates/welcome.html
scripts/leselys