Metadata-Version: 1.1
Name: leselys
Version: 0.2.7
Summary: I'm Leselys, your very elegant RSS reader.
Home-page: https://github.com/toxinu/leselys
Author: toxinu
Author-email: toxinu@gmail.com
License: Leselys
